tacomaker/__init__.py
tacomaker/create.py
tacomaker/datamodel/__init__.py
tacomaker/datamodel/sample.py
tacomaker/datamodel/taco.py
tacomaker/datamodel/tortilla.py
tacomaker/edit.py
tacomaker/sample/datamodel.py
tacomaker/sample/extensions/__init__.py
tacomaker/sample/extensions/scaling.py
tacomaker/sample/extensions/stac.py
tacomaker/sample/extensions/stats.py
tacomaker/taco/__init__.py
tacomaker/taco/datamodel.py
tacomaker/taco/extensions/labels.py
tacomaker/taco/extensions/opticaldata.py
tacomaker/taco/extensions/opticaldata_utils.py
tacomaker/taco/extensions/scientific.py
tacomaker/taco/extensions/split.py
tacomaker/tortilla/datamodel.py
tacomaker/tortilla/extensions/majortom.py
tacomaker/tortilla/extensions/territorial.py
tacomaker/tortilla/extensions/territorial_products.py
tacomaker/tortilla/extensions/territorial_utils.py
tacomaker/version.py
tacomaker-0.1.0.dist-info/LICENSE
tacomaker-0.1.0.dist-info/METADATA
tacomaker-0.1.0.dist-info/WHEEL
tacomaker-0.1.0.dist-info/RECORD
